{
    "type": "FeatureCollection",
    "features": [
      {
        "type": "Feature",
        "properties": {
          "regiao": "Florianopolis"
        },
        "geometry": {
          "type": "Point",
          "coordinates": [-48.5480, -27.5954]
        }
      },
      {
        "type": "Feature",
        "properties": {
          "regiao": "Joinville"
        },
        "geometry": {
          "type": "Point",
          "coordinates": [-48.8461, -26.3045]
        }
      },
      {
        "type": "Feature",
        "properties": {
          "regiao": "Blumenau"
        },
        "geometry": {
          "type": "Point",
          "coordinates": [-49.0703, -26.9155]
        }
      },
      {
        "type": "Feature",
        "properties": {
          "regiao": "Chapeco"
        },
        "geometry": {
          "type": "Point",
          "coordinates": [-52.6152, -27.1005]
        }
      },
      {
        "type": "Feature",
        "properties": {
          "regiao": "Criciuma"
        },
        "geometry": {
          "type": "Point",
          "coordinates": [-49.3726, -28.6723]
        }
      },
      {
        "type": "Feature",
        "properties": {
          "regiao": "Lages"
        },
        "geometry": {
          "type": "Point",
          "coordinates": [-50.3260, -27.8130]
        }
      },
      {
        "type": "Feature",
        "properties": {
          "regiao": "Itajai"
        },
        "geometry": {
          "type": "Point",
          "coordinates": [-48.6705, -26.9106]
        }
      },
      {
        "type": "Feature",
        "properties": {
          "regiao": "SaoMigueldoOeste"
        },
        "geometry": {
          "type": "Point",
          "coordinates": [-53.5165, -26.7242]
        }
      }
    ]
  }
  